fixalign/__init__.py
fixalign/block_class.py
fixalign/find_small_exon.py
fixalign/fix_small_exon.py
fixalign/fix_small_exon_multiproc.py
fixalign/run_fixalign.py
fixalign/version.py
fixalign-0.2.10.dist-info/LICENSE
fixalign-0.2.10.dist-info/METADATA
fixalign-0.2.10.dist-info/WHEEL
fixalign-0.2.10.dist-info/entry_points.txt
fixalign-0.2.10.dist-info/top_level.txt
fixalign-0.2.10.dist-info/RECORD
