Metadata-Version: 2.1
Name: fixalign
Version: 0.2.10
Summary: find and fix missed small exons
Home-page: https://github.com/zhenLiuExplr/fixalign-project
Author: Zhen Liu
Author-email: liuzhen2018@sibs.ac.cn
License: UNKNOWN
Platform: UNKNOWN
Classifier: Programming Language :: Python :: 3
Classifier: License :: OSI Approved :: MIT License
Classifier: Operating System :: POSIX :: Linux
Requires-Python: >=3
Requires-Dist: numpy
Requires-Dist: pandas
Requires-Dist: pysam
Requires-Dist: parasail (>=1.1.17)
